cropmask/__init__.py
cropmask/datasets.py
cropmask/grid_pooled.py
cropmask/io_utils.py
cropmask/label_prep.py
cropmask/misc.py
cropmask/model_configs.py
cropmask/preprocess.py
cropmask/preprocess_config.yaml
cropmask/run_cropmask.py
cropmask/run_preprocess.py
cropmask/sequential_grid.py
cropmask/azuresetup/__init__.py
cropmask/azuresetup/create_workspace.py
cropmask/azuresetup/get_SAS.py
cropmask/azuresetup/setup_utils.py
cropmask/download/__init__.py
cropmask/download/download_utils.py
cropmask/download/order_landsat_to_azure.py
cropmask/mrcnn/__init__.py
cropmask/mrcnn/config.py
cropmask/mrcnn/model.py
cropmask/mrcnn/parallel_model.py
cropmask/mrcnn/utils.py
cropmask/mrcnn/visualize.py
cropmask/tests/data-test.py
cropmask/tests/download_tests.py
cropmask/tests/preprocess_tests.py
cropmask-0.1.dist-info/LICENSE
cropmask-0.1.dist-info/WHEEL
cropmask-0.1.dist-info/METADATA
cropmask-0.1.dist-info/RECORD
