Metadata-Version: 2.1
Name: cropmask
Version: 0.1
Summary: AI for Earth project to map center pivots and monitor crop water use.
Home-page: https://github.com/ecohydro/CropMask_RCNN
License: UNKNOWN
Keywords: segmentation keras landsat agriculture
Author: Ryan Avery
Author-email: ravery@ucsb.edu
Classifier: License :: OSI Approved :: MIT License
Classifier: Development Status :: 2 - Pre-Alpha
Classifier: Environment :: Console
Classifier: Intended Audience :: Developers
Classifier: Intended Audience :: Information Technology
Classifier: Intended Audience :: Education
Classifier: Intended Audience :: Science/Research
Classifier: Natural Language :: English
Classifier: Operating System :: OS Independent
Classifier: Topic :: Scientific/Engineering :: Artificial Intelligence
Classifier: Topic :: Scientific/Engineering :: Image Recognition
Classifier: Topic :: Scientific/Engineering :: Visualization
Classifier: Topic :: Scientific/Engineering :: GIS
Classifier: Programming Language :: Python :: 3.6
